dgutils/__init__.py
dgutils/colors.py
dgutils/pypov.py
dgutils/savehtml.py
dgutils/wikiupload.py
dgutils-0.2.5.dist-info/LICENSE
dgutils-0.2.5.dist-info/METADATA
dgutils-0.2.5.dist-info/WHEEL
dgutils-0.2.5.dist-info/top_level.txt
dgutils-0.2.5.dist-info/RECORD
